{"/*":["X-Frame-Options: DENY","X-XSS-Protection: 1; mode=block","X-Content-Type-Options: nosniff","Referrer-Policy: same-origin"],"/component---cache-caches-gatsby-plugin-offline-app-shell-js-bebaafd30fc720d83ba7.js":["Cache-Control: public, max-age=31536000, immutable"],"/styles.d496ceb7b3ff14acce33.css":["Cache-Control: public, max-age=31536000, immutable"],"/a3336d3c033a5ec9d59a088cb032c68b95c64a61-583abdd0a1c95d701c44.js":["Cache-Control: public, max-age=31536000, immutable"],"/component---src-pages-404-tsx-23db498756fa8999ee9f.js":["Cache-Control: public, max-age=31536000, immutable"],"/component---src-pages-index-tsx-7c4e1a26c8bae090b23c.js":["Cache-Control: public, max-age=31536000, immutable"],"/component---src-pages-soon-tsx-c04a589206f0060bcaed.js":["Cache-Control: public, max-age=31536000, immutable"],"/webpack-runtime-8631c659e421f1292422.js":["Cache-Control: public, max-age=31536000, immutable"],"/framework-2f4f101ae0b1b7971378.js":["Cache-Control: public, max-age=31536000, immutable"],"/app-50c6d44ae588a4b2f94c.js":["Cache-Control: public, max-age=31536000, immutable"],"/static/*":["Cache-Control: public, max-age=31536000, immutable"],"/sw.js":["Cache-Control: public, max-age=0, must-revalidate"],"/offline-plugin-app-shell-fallback/":["Link: </webpack-runtime-8631c659e421f1292422.js>; rel=preload; as=script; nopush","Link: </framework-2f4f101ae0b1b7971378.js>; rel=preload; as=script; nopush","Link: </app-50c6d44ae588a4b2f94c.js>; rel=preload; as=script; nopush","Link: </component---cache-caches-gatsby-plugin-offline-app-shell-js-bebaafd30fc720d83ba7.js>; rel=preload; as=script; nopush","Link: </page-data/app-data.json>; rel=preload; as=fetch; crossorigin; nopush","Link: </page-data/offline-plugin-app-shell-fallback/page-data.json>; rel=preload; as=fetch; crossorigin; nopush"],"/404/":["Link: </webpack-runtime-8631c659e421f1292422.js>; rel=preload; as=script; nopush","Link: </framework-2f4f101ae0b1b7971378.js>; rel=preload; as=script; nopush","Link: </app-50c6d44ae588a4b2f94c.js>; rel=preload; as=script; nopush","Link: </a3336d3c033a5ec9d59a088cb032c68b95c64a61-583abdd0a1c95d701c44.js>; rel=preload; as=script; nopush","Link: </component---src-pages-404-tsx-23db498756fa8999ee9f.js>; rel=preload; as=script; nopush","Link: </page-data/app-data.json>; rel=preload; as=fetch; crossorigin; nopush","Link: </page-data/404/page-data.json>; rel=preload; as=fetch; crossorigin; nopush"],"/404.html":["Link: </webpack-runtime-8631c659e421f1292422.js>; rel=preload; as=script; nopush","Link: </framework-2f4f101ae0b1b7971378.js>; rel=preload; as=script; nopush","Link: </app-50c6d44ae588a4b2f94c.js>; rel=preload; as=script; nopush","Link: </a3336d3c033a5ec9d59a088cb032c68b95c64a61-583abdd0a1c95d701c44.js>; rel=preload; as=script; nopush","Link: </component---src-pages-404-tsx-23db498756fa8999ee9f.js>; rel=preload; as=script; nopush","Link: </page-data/app-data.json>; rel=preload; as=fetch; crossorigin; nopush","Link: </page-data/404.html/page-data.json>; rel=preload; as=fetch; crossorigin; nopush"],"/":["Link: </webpack-runtime-8631c659e421f1292422.js>; rel=preload; as=script; nopush","Link: </framework-2f4f101ae0b1b7971378.js>; rel=preload; as=script; nopush","Link: </app-50c6d44ae588a4b2f94c.js>; rel=preload; as=script; nopush","Link: </a3336d3c033a5ec9d59a088cb032c68b95c64a61-583abdd0a1c95d701c44.js>; rel=preload; as=script; nopush","Link: </component---src-pages-index-tsx-7c4e1a26c8bae090b23c.js>; rel=preload; as=script; nopush","Link: </page-data/app-data.json>; rel=preload; as=fetch; crossorigin; nopush","Link: </page-data/index/page-data.json>; rel=preload; as=fetch; crossorigin; nopush"],"/soon/":["Link: </webpack-runtime-8631c659e421f1292422.js>; rel=preload; as=script; nopush","Link: </framework-2f4f101ae0b1b7971378.js>; rel=preload; as=script; nopush","Link: </app-50c6d44ae588a4b2f94c.js>; rel=preload; as=script; nopush","Link: </component---src-pages-soon-tsx-c04a589206f0060bcaed.js>; rel=preload; as=script; nopush","Link: </page-data/app-data.json>; rel=preload; as=fetch; crossorigin; nopush","Link: </page-data/soon/page-data.json>; rel=preload; as=fetch; crossorigin; nopush"]}